vru/__init__.py
vru/datetime.py
vru/profile.py
vru/translate.py
vru/crypto/__init__.py
vru/crypto/sign.py
vru/exceptions/__init__.py
vru/exceptions/exceptions.py
vru/exceptions/handlers.py
vru/middleware/__init__.py
vru/middleware/localization.py
vr.utils-0.3.0.dist-info/LICENSE
vr.utils-0.3.0.dist-info/METADATA
vr.utils-0.3.0.dist-info/WHEEL
vr.utils-0.3.0.dist-info/top_level.txt
vr.utils-0.3.0.dist-info/RECORD
