Metadata-Version: 2.1
Name: vr.utils
Version: 0.3.0
Summary: Python utilities.
Home-page: UNKNOWN
Author: Vladimir Rukavishnikov
Author-email: RukavishnikovVV@mail.ru
License: UNKNOWN
Platform: UNKNOWN
Classifier: Programming Language :: Python :: 3
Classifier: License :: OSI Approved :: MIT License
Classifier: Operating System :: OS Independent
Requires-Python: >=3.10
License-File: LICENSE
Requires-Dist: fastapi (>=0.78.0)
Requires-Dist: tortoise-orm (>=0.19.0)
Requires-Dist: loguru (>=0.6.0)
